LICENSE.txt
README.txt
VERSION.txt
recaptcha.py
setup.cfg
setup.py
recaptcha.egg-info/PKG-INFO
recaptcha.egg-info/SOURCES.txt
recaptcha.egg-info/dependency_links.txt
recaptcha.egg-info/not-zip-safe
recaptcha.egg-info/top_level.txt