Metadata-Version: 1.1
Name: recaptcha
Version: 1.0b1
Summary: Pythonic, well documented and fully featured reCAPTCHA client
Home-page: http://packages.python.org/recaptcha
Author: 2degrees Limited
Author-email: 2degrees-floss@googlegroups.com
License: BSD (http://dev.2degreesnetwork.com/p/2degrees-license.html)
Download-URL: http://pypi.python.org/pypi/recaptcha/
Keywords: recaptcha captcha
Platform: UNKNOWN
Classifier: Development Status :: 4 - Beta
Classifier: Environment :: Web Environment
Classifier: Intended Audience :: Developers
Classifier: License :: OSI Approved :: BSD License
Classifier: Natural Language :: English
Classifier: Operating System :: OS Independent
Classifier: Programming Language :: Python :: 2.6
Classifier: Programming Language :: Python :: 2.7
Classifier: Topic :: Internet :: WWW/HTTP :: Dynamic Content
Classifier: Topic :: Security
